AUTHORS.rst
CONTRIBUTING.rst
HISTORY.rst
LICENSE
MANIFEST.in
README.rst
setup.cfg
setup.py
bin/yawap
docs/Makefile
docs/authors.rst
docs/conf.py
docs/contributing.rst
docs/history.rst
docs/index.rst
docs/installation.rst
docs/make.bat
docs/readme.rst
docs/usage.rst
tests/__init__.py
tests/test_yawap.py
yawap/__init__.py
yawap/iso_country_codes.py
yawap/service.py
yawap/wpasupplicantconf.py
yawap/yawap_tools.py
yawap.egg-info/PKG-INFO
yawap.egg-info/SOURCES.txt
yawap.egg-info/dependency_links.txt
yawap.egg-info/not-zip-safe
yawap.egg-info/requires.txt
yawap.egg-info/top_level.txt