Metadata-Version: 1.1
Name: yawap
Version: 0.0.8
Summary: Access point and wifi connection tool
Home-page: https://github.com/lukh/yawap
Author: Vivien Henry
Author-email: vivien.henry@inductivebrain.fr
License: MIT license
Keywords: yawap
Platform: UNKNOWN
Classifier: Development Status :: 2 - Pre-Alpha
Classifier: Intended Audience :: Developers
Classifier: License :: OSI Approved :: MIT License
Classifier: Natural Language :: English
Classifier: Programming Language :: Python :: 2
Classifier: Programming Language :: Python :: 2.7
Classifier: Programming Language :: Python :: 3
Classifier: Programming Language :: Python :: 3.4
Classifier: Programming Language :: Python :: 3.5
Classifier: Programming Language :: Python :: 3.6
Classifier: Programming Language :: Python :: 3.7
